scontoolkit/__init__.py
scontoolkit/interfaces/__init__.py
scontoolkit/interfaces/base.py
scontoolkit/interfaces/dsp/__init__.py
scontoolkit/interfaces/dsp/catalog.py
scontoolkit/interfaces/dsp/metadb.py
scontoolkit/interfaces/dsp/router.py
scontoolkit/interfaces/slg/__init__.py
scontoolkit/interfaces/slg/negotiation.py
scontoolkit/models/__init__.py
scontoolkit/models/base.py
scontoolkit/models/dsp/__init__.py
scontoolkit/models/dsp/base.py
scontoolkit/models/dsp/v2025_1_rc2/__init__.py
scontoolkit/models/dsp/v2025_1_rc2/catalog.py
scontoolkit/models/dsp/v2025_1_rc2/common.py
scontoolkit/models/dsp/v2025_1_rc2/contract_negotiation_protocol.py
scontoolkit/models/dsp/v2025_1_rc2/low_level.py
scontoolkit/models/odrl/__init__.py
scontoolkit/models/slg/__init__.py
scontoolkit/models/slg/models.py
scontoolkit/models/slg/negotitation.py
scontoolkit/odrl/__init__.py
scontoolkit/services/__init__.py
scontoolkit/services/extension_handler.py
scontoolkit/services/meta_db_service.py
scontoolkit-0.0.2b12.dist-info/METADATA
scontoolkit-0.0.2b12.dist-info/WHEEL
scontoolkit-0.0.2b12.dist-info/top_level.txt
scontoolkit-0.0.2b12.dist-info/RECORD
